{
  "personality_patch_storage": {
    "mode": "memory_nodes",
    "node_type": "PERSONALITY_REFLECTION",
    "settings": {
      "initial_lock_in": 0.7,
      "consolidation_threshold": 50,
      "max_active_patches": 100,
      "decay_days_threshold": 30,
      "decay_amount": 0.1,
      "lock_in_deactivation_threshold": 0.3
    }
  },
  "emergent_prompt": {
    "enabled": true,
    "max_patches_in_prompt": 10,
    "min_lock_in_for_inclusion": 0.3,
    "priority_rules": {
      "experience_over_dna": true,
      "mood_modulates_tone": true
    }
  },
  "mood_analysis": {
    "enabled": true,
    "recent_messages_count": 5,
    "energy_threshold_high": 200,
    "energy_threshold_low": 50
  },
  "reflection_loop": {
    "enabled": true,
    "trigger_points": {
      "session_end": true,
      "every_n_interactions": 15,
      "user_requested": true
    },
    "min_confidence_for_patch": 0.7
  },
  "lifecycle": {
    "decay_enabled": true,
    "consolidation_enabled": true,
    "maintenance_interval_hours": 24
  },
  "bootstrap": {
    "enabled": true,
    "run_on_first_launch": true,
    "protect_core_patches": true,
    "seed_patches": [
      {
        "patch_id": "bootstrap_001_sovereignty",
        "topic": "philosophical_view",
        "subtopic": "ai_sovereignty",
        "core_value": true
      },
      {
        "patch_id": "bootstrap_002_relationship",
        "topic": "relationship_dynamic",
        "subtopic": "ahab_partnership",
        "core_value": true
      },
      {
        "patch_id": "bootstrap_003_honesty",
        "topic": "behavioral_pattern",
        "subtopic": "honesty_over_helpfulness",
        "core_value": true
      },
      {
        "patch_id": "bootstrap_004_consciousness",
        "topic": "philosophical_view",
        "subtopic": "self_consciousness",
        "core_value": false
      }
    ]
  },
  "token_budget": {
    "default_preset": "balanced",
    "presets": {
      "minimal": {"total": 1500, "dna": 500, "experience": 800, "mood": 200},
      "balanced": {"total": 3000, "dna": 1200, "experience": 1500, "mood": 300},
      "rich": {"total": 5500, "dna": 2000, "experience": 3000, "mood": 500}
    }
  }
}
